xor_cipher_core-1.2.0.dist-info/METADATA
xor_cipher_core-1.2.0.dist-info/WHEEL
xor_cipher_core-1.2.0.dist-info/licenses/LICENSE
xor_cipher_core.libs/libgcc_s-b5472b99.so.1
xor_cipher_core/__init__.py
xor_cipher_core/_xor_cipher_core.cpython-39-i386-linux-gnu.so
xor_cipher_core/_xor_cipher_core.pyi
xor_cipher_core/py.typed
xor_cipher_core-1.2.0.dist-info/RECORD
