Metadata-Version: 2.4
Name: xor-cipher-core
Version: 1.2.0
Classifier: Development Status :: 5 - Production/Stable
Classifier: Intended Audience :: Developers
Classifier: License :: OSI Approved :: MIT License
Classifier: Operating System :: OS Independent
Classifier: Programming Language :: Rust
Classifier: Programming Language :: Python
Classifier: Programming Language :: Python :: 3
Classifier: Programming Language :: Python :: 3 :: Only
Classifier: Programming Language :: Python :: 3.9
Classifier: Programming Language :: Python :: 3.10
Classifier: Programming Language :: Python :: 3.11
Classifier: Programming Language :: Python :: 3.12
Classifier: Programming Language :: Python :: 3.13
Classifier: Topic :: Utilities
Classifier: Typing :: Typed
License-File: LICENSE
Summary: Simple, reusable and optimized XOR ciphers in Python (core).
Keywords: xor,cipher,core
Author: GDPS App <hello@gdps.app>
Author-email: GDPS App <hello@gdps.app>
License: MIT
Requires-Python: >=3.9
Project-URL: Homepage, https://github.com/GDPSApp/xor-cipher-core
Project-URL: Documentation, https://xor-cipher.gdps.app/
Project-URL: Issues, https://github.com/GDPSApp/xor-cipher-core/issues
Project-URL: Repository, https://github.com/GDPSApp/xor-cipher-core
